{
    "ark": "ark:/21198/z1156883",
    "reconstruction": false,
    "type": {
        "id": "manuscript",
        "label": "Manuscript"
    },
    "shelfmark": "Sinai Syriac NF M 61",
    "extent": "3 ff.",
    "weight": "8.5 g",
    "dim": "164 x 118 x 4.0 mm",
    "state": {
        "id": "folio, bifolio",
        "label": "Folio(s),Bifolio(s)"
    },
    "part": [
        {
            "label": "Codicological Unit",
            "support": [
                {
                    "id": "parchment",
                    "label": "Parchment"
                }
            ],
            "layer": [
                {
                    "id": "ark:/21198/s1xc98",
                    "label": "Overtext Layer",
                    "type": {
                        "id": "overtext",
                        "label": "Overtext"
                    },
                    "locus": "<NA>"
                }
            ]
        }
    ],
    "location": [
        {
            "id": "sinai-nf",
            "collection": "New Finds",
            "repository": "St. Catherine's Monastery of the Sinai"
        }
    ],
    "bib": [
        {
            "id": "b1a3a9c9-ed90-440a-9e37-fade7a17796d",
            "type": {
                "id": " ref",
                "label": "Reference"
            },
            "range": "[M61N], pp. 193"
        }
    ],
    "iiif": [
        {
            "type": {
                "id": "main",
                "label": "Main"
            },
            "manifest": "https://iiif.library.ucla.edu/ark%3A%2F21198%2Fz1156883/manifest",
            "text_direction": "right-to-left",
            "behavior": "paged",
            "thumbnail": "https://iiif.sinaimanuscripts.library.ucla.edu/iiif/2/ark%3A%2F21198%2Fz1156883%2F1x26mh8n/full/!200,200/0/default.jpg"
        }
    ]
}