{
    "ark": "ark:/21198/s1kk8v",
    "reconstruction": false,
    "label": "Sinai Syriac 225, Overtext (Melkite)",
    "state": {
        "id": "overtext",
        "label": "Overtext"
    },
    "writing": [
        {
            "script": [
                {
                    "id": "melkite",
                    "label": "Melkite",
                    "writing_system": "Syriac"
                }
            ]
        }
    ],
    "text_unit": [
        {
            "id": "ark:/21198/s1d674",
            "label": "Item 1"
        }
    ],
    "features": [
        {
            "id": "deco-geometric",
            "label": "Decoration, Geometric"
        },
        {
            "id": "deco-vegetative",
            "label": "Decoration, Vegetative"
        },
        {
            "id": "headpiece",
            "label": "Headpiece(s)"
        },
        {
            "id": "fragment",
            "label": "Fragment"
        },
        {
            "id": "table",
            "label": "Table(s)"
        }
    ],
    "assoc_date": [
        {
            "type": {
                "id": "origin",
                "label": "Date of Origin"
            },
            "value": "13th c.",
            "iso": {
                "not_before": "1201",
                "not_after": "1300"
            }
        }
    ],
    "note": [
        {
            "type": {
                "id": "ornamentation",
                "label": "Ornamentation Note"
            },
            "value": "Ornate and minor geometric and vegetative headpieces throughout, beginning f. 2r"
        },
        {
            "type": {
                "id": "ornamentation",
                "label": "Ornamentation Note"
            },
            "value": "Joined circular tables with Greek text, f. 572v, fragment"
        }
    ],
    "parent": [
        "ark:/21198/z1ms5bh5"
    ]
}